mcadminbot/__init__.py
mcadminbot/bot/__init__.py
mcadminbot/bot/bot.py
mcadminbot/bot/exceptions.py
mcadminbot/bot/minecraftcommands.py
mcadminbot/bot/systemcommands.py
mcadminbot/bot/utils.py
mcadminbot/config.py
mcadminbot/defaults.yaml
mcadminbot/entry.py
mcadminbot-1.0.2.dist-info/entry_points.txt
mcadminbot-1.0.2.dist-info/LICENSE
mcadminbot-1.0.2.dist-info/WHEEL
mcadminbot-1.0.2.dist-info/METADATA
mcadminbot-1.0.2.dist-info/RECORD
